sai_banner/__init__.py
sai_banner/core.py
sai_banner-0.1.0.dist-info/METADATA
sai_banner-0.1.0.dist-info/WHEEL
sai_banner-0.1.0.dist-info/top_level.txt
sai_banner-0.1.0.dist-info/RECORD
